t4flib/__init__.py
t4flib/config.py
t4flib/data_helper.py
t4flib/file_helper.py
t4flib/filetransfer_helper.py
t4flib/functional_helper.py
t4flib/gcloud_helper.py
t4flib/log_helper.py
t4flib-0.3.10.dist-info/METADATA
t4flib-0.3.10.dist-info/WHEEL
t4flib-0.3.10.dist-info/top_level.txt
t4flib-0.3.10.dist-info/RECORD
