Metadata-Version: 2.1
Name: t4flib
Version: 0.3.10
Summary: Librairie de fonction utiles pour T4F
Home-page: http://gitlab.dev.fr.auchan.com/tech4finance/t4flib.git
Author: Corentin DEVROUETE
Author-email: cdevrouete@advanced-schema.com
License: MIT
Platform: UNKNOWN
Classifier: Development Status :: 3 - Alpha
Classifier: Intended Audience :: Developers
Classifier: License :: OSI Approved :: MIT License
Classifier: Programming Language :: Python :: 3.8
Requires-Dist: google-cloud-bigquery
Requires-Dist: google-cloud-storage
Requires-Dist: colorama
Requires-Dist: pandas
Requires-Dist: google-auth
